[{"SUM_DENDA":82424246,"SUM_REALISASI":1255436896,"SUM_KETETAPAN":1362189737,"TAHUN_PAJAK":"2013"},{"SUM_DENDA":106110536,"SUM_REALISASI":1893319869,"SUM_KETETAPAN":1991366056,"TAHUN_PAJAK":"2014"},{"SUM_DENDA":161651872,"SUM_REALISASI":2129943776,"SUM_KETETAPAN":2243913827,"TAHUN_PAJAK":"2015"},{"SUM_DENDA":258447132,"SUM_REALISASI":3824888888,"SUM_KETETAPAN":3973674362,"TAHUN_PAJAK":"2016"},{"SUM_DENDA":428158935,"SUM_REALISASI":5343046818,"SUM_KETETAPAN":6035961585,"TAHUN_PAJAK":"2017"},{"SUM_DENDA":605430252,"SUM_REALISASI":5441134195,"SUM_KETETAPAN":6480991757,"TAHUN_PAJAK":"2018"},{"SUM_DENDA":1092079442,"SUM_REALISASI":7627732203,"SUM_KETETAPAN":9487981177,"TAHUN_PAJAK":"2019"},{"SUM_DENDA":1289740930,"SUM_REALISASI":7087166826,"SUM_KETETAPAN":9371853757,"TAHUN_PAJAK":"2020"},{"SUM_DENDA":1099938884,"SUM_REALISASI":7526935157,"SUM_KETETAPAN":9444154787,"TAHUN_PAJAK":"2021"},{"SUM_DENDA":947776945,"SUM_REALISASI":9977167508,"SUM_KETETAPAN":12260192178,"TAHUN_PAJAK":"2022"},{"SUM_DENDA":199378885,"SUM_REALISASI":9771622710,"SUM_KETETAPAN":12090574568,"TAHUN_PAJAK":"2023"},{"SUM_DENDA":48390,"SUM_REALISASI":5174278041,"SUM_KETETAPAN":12188812113,"TAHUN_PAJAK":"2024"}]